hubmap_search_sdk/__init__.py
hubmap_search_sdk/_base_client.py
hubmap_search_sdk/_client.py
hubmap_search_sdk/_compat.py
hubmap_search_sdk/_constants.py
hubmap_search_sdk/_exceptions.py
hubmap_search_sdk/_files.py
hubmap_search_sdk/_models.py
hubmap_search_sdk/_qs.py
hubmap_search_sdk/_resource.py
hubmap_search_sdk/_response.py
hubmap_search_sdk/_streaming.py
hubmap_search_sdk/_types.py
hubmap_search_sdk/_version.py
hubmap_search_sdk/py.typed
hubmap_search_sdk/_utils/__init__.py
hubmap_search_sdk/_utils/_compat.py
hubmap_search_sdk/_utils/_datetime_parse.py
hubmap_search_sdk/_utils/_logs.py
hubmap_search_sdk/_utils/_proxy.py
hubmap_search_sdk/_utils/_reflection.py
hubmap_search_sdk/_utils/_resources_proxy.py
hubmap_search_sdk/_utils/_streams.py
hubmap_search_sdk/_utils/_sync.py
hubmap_search_sdk/_utils/_transform.py
hubmap_search_sdk/_utils/_typing.py
hubmap_search_sdk/_utils/_utils.py
hubmap_search_sdk/lib/.keep
hubmap_search_sdk/resources/__init__.py
hubmap_search_sdk/resources/add.py
hubmap_search_sdk/resources/clear_docs.py
hubmap_search_sdk/resources/indices.py
hubmap_search_sdk/resources/mapping.py
hubmap_search_sdk/resources/mget.py
hubmap_search_sdk/resources/param_search.py
hubmap_search_sdk/resources/reindex.py
hubmap_search_sdk/resources/scroll_search.py
hubmap_search_sdk/resources/search.py
hubmap_search_sdk/resources/update.py
hubmap_search_sdk/types/__init__.py
hubmap_search_sdk/types/add_create_document_params.py
hubmap_search_sdk/types/add_create_document_with_index_params.py
hubmap_search_sdk/types/add_update_document_with_scope_params.py
hubmap_search_sdk/types/index_list_response.py
hubmap_search_sdk/types/mget_retrieve_multiple_by_index_params.py
hubmap_search_sdk/types/mget_retrieve_multiple_params.py
hubmap_search_sdk/types/param_search_execute_params.py
hubmap_search_sdk/types/scroll_search_create_params.py
hubmap_search_sdk/types/search_execute_index_query_params.py
hubmap_search_sdk/types/search_execute_query_params.py
hubmap_search_sdk-1.0.0a38.dist-info/METADATA
hubmap_search_sdk-1.0.0a38.dist-info/WHEEL
hubmap_search_sdk-1.0.0a38.dist-info/licenses/LICENSE
hubmap_search_sdk-1.0.0a38.dist-info/RECORD
